encrusted-1.0.1.dist-info/METADATA
encrusted-1.0.1.dist-info/WHEEL
encrusted-1.0.1.dist-info/license_files/LICENSE
encrusted/_decode.py
encrusted/__init__.py
encrusted/_encode.py
encrusted/_encrusted_ext.pyi
encrusted/_encrusted_ext.cpython-311-darwin.so
encrusted-1.0.1.dist-info/RECORD
